{
  "gitSyncId": "692456a78a3f3113425a1717_2cc09094-57c4-421c-b1ff-56c77fa23a9e",
  "id": "Hakerton_DeleteFile",
  "pluginId": "amazons3-plugin",
  "pluginType": "DB",
  "unpublishedAction": {
    "actionConfiguration": {
      "encodeParamsToggle": true,
      "formData": {
        "body": {
          "componentData": "{\n\t\"data\": \"null\"\n}",
          "data": "{\n\t\"data\": \"null\"\n}",
          "viewType": "component"
        },
        "bucket": {
          "componentData": "hakerton",
          "data": "hakerton",
          "viewType": "component"
        },
        "command": {
          "componentData": "DELETE_FILE",
          "data": "DELETE_FILE",
          "viewType": "component"
        },
        "path": {
          "componentData": "{{File_List.selectedItem.fileName}}",
          "data": "{{File_List.selectedItem.fileName}}",
          "viewType": "component"
        }
      },
      "paginationType": "NONE",
      "timeoutInMillisecond": 10000
    },
    "confirmBeforeExecute": false,
    "datasource": {
      "id": "S3",
      "isAutoGenerated": false,
      "name": "S3",
      "pluginId": "amazons3-plugin"
    },
    "dynamicBindingPathList": [
      {
        "key": "formData.path.data"
      }
    ],
    "name": "DeleteFile",
    "pageId": "Hakerton",
    "runBehaviour": "MANUAL",
    "userSetOnLoad": false
  }
}